anot-0.0.7.dist-info/METADATA
anot-0.0.7.dist-info/WHEEL
anot-0.0.7.dist-info/entry_points.txt
anot-0.0.7.dist-info/licenses/LICENSE
anot/py.typed
anot/_anot.pyi
anot/__init__.py
anot/_anot.cp39-win32.pyd
anot-0.0.7.dist-info/RECORD
