Metadata-Version: 2.4
Name: anot
Version: 0.0.7
Classifier: Development Status :: 3 - Alpha
Classifier: Programming Language :: Rust
Classifier: Programming Language :: Python :: Implementation :: CPython
Classifier: Programming Language :: Python :: 3.9
Classifier: Programming Language :: Python :: 3.10
Classifier: Programming Language :: Python :: 3.11
Classifier: Programming Language :: Python :: 3.12
Classifier: Operating System :: OS Independent
Classifier: Topic :: Software Development :: Libraries :: Python Modules
Classifier: Topic :: Scientific/Engineering
Classifier: Intended Audience :: Developers
Classifier: Intended Audience :: Information Technology
Classifier: Typing :: Typed
Requires-Dist: maturin >=1.7.8
License-File: LICENSE
Summary: Extract @annotations from source code comments
Author-email: Rory Byrne <rory@rory.bio>
License: MIT
Requires-Python: >=3.9
Project-URL: Homepage, https://github.com/flywhl/anot
Project-URL: Repository, https://github.com/flywhl/anot
Project-URL: Documentation, https://github.com/flywhl/anot#readme
Project-URL: Bug Tracker, https://github.com/flywhl/anot/issues
